.mina/qqapi.toml
avilla/qqapi/__init__.py
avilla/qqapi/account.py
avilla/qqapi/audit/__init__.py
avilla/qqapi/audit/event.py
avilla/qqapi/audit/metadata.py
avilla/qqapi/audit/store.py
avilla/qqapi/capability.py
avilla/qqapi/collector/__init__.py
avilla/qqapi/collector/connection.py
avilla/qqapi/connection/__init__.py
avilla/qqapi/connection/base.py
avilla/qqapi/connection/util.py
avilla/qqapi/connection/webhook.py
avilla/qqapi/connection/ws_client.py
avilla/qqapi/const.py
avilla/qqapi/element.py
avilla/qqapi/exception.py
avilla/qqapi/perform/__init__.py
avilla/qqapi/perform/action/__init__.py
avilla/qqapi/perform/action/channel.py
avilla/qqapi/perform/action/guild.py
avilla/qqapi/perform/action/guild_member.py
avilla/qqapi/perform/action/message.py
avilla/qqapi/perform/action/role.py
avilla/qqapi/perform/action/user.py
avilla/qqapi/perform/context.py
avilla/qqapi/perform/event/__init__.py
avilla/qqapi/perform/event/activity.py
avilla/qqapi/perform/event/audit.py
avilla/qqapi/perform/event/message.py
avilla/qqapi/perform/event/metadata.py
avilla/qqapi/perform/event/relationship.py
avilla/qqapi/perform/message/deserialize.py
avilla/qqapi/perform/message/serialize.py
avilla/qqapi/perform/query.py
avilla/qqapi/perform/resource_fetch.py
avilla/qqapi/protocol.py
avilla/qqapi/resource.py
avilla/qqapi/role/__init__.py
avilla/qqapi/role/capability.py
avilla/qqapi/role/metadata.py
avilla/qqapi/service.py
avilla/qqapi/utils.py
avilla_qqapi-1.0.0a33.dist-info/METADATA
avilla_qqapi-1.0.0a33.dist-info/WHEEL
avilla_qqapi-1.0.0a33.dist-info/licenses/LICENSE
avilla_qqapi-1.0.0a33.dist-info/RECORD
